{
   "field": [
      "Season",
      "流動資產",
      "現金及約當現金",
      "備供出售金融資產－流動淨額",
      "應收帳款淨額",
      "應收建造合約款",
      "其他應收款淨額",
      "本期所得稅資產",
      "存貨",
      "預付款項",
      "其他流動資產",
      "流動資產合計",
      "非流動資產",
      "備供出售金融資產－非流動淨額",
      "採用權益法之投資淨額",
      "不動產、廠房及設備",
      "投資性不動產淨額",
      "遞延所得稅資產",
      "其他非流動資產",
      "非流動資產合計",
      "資產總計",
      "流動負債",
      "短期借款",
      "應付短期票券",
      "應付票據",
      "應付帳款",
      "應付建造合約款",
      "其他應付款",
      "本期所得稅負債",
      "負債準備－流動",
      "其他流動負債",
      "流動負債合計",
      "非流動負債",
      "長期借款",
      "負債準備－非流動",
      "遞延所得稅負債",
      "其他非流動負債",
      "非流動負債合計",
      "負債總計",
      "歸屬於母公司業主之權益",
      "股本",
      "普通股股本",
      "股本合計",
      "資本公積",
      "資本公積－發行溢價",
      "資本公積合計",
      "保留盈餘",
      "法定盈餘公積",
      "特別盈餘公積",
      "未分配盈餘（或待彌補虧損）",
      "保留盈餘合計",
      "其他權益",
      "國外營運機構財務報表換算之兌換差額",
      "備供出售金融資產未實現損益",
      "其他權益合計",
      "歸屬於母公司業主之權益合計",
      "非控制權益",
      "權益總計",
      "負債及權益總計",
      "待註銷股本股數（單位：股）",
      "預收股款（權益項下）之約當發行股數（單位：股）",
      "母公司暨子公司所持有之母公司庫藏股股數（單位：股）"
   ],
   "data": {
      "Season": "2015/3",
      "流動資產": null,
      "現金及約當現金": 915637,
      "備供出售金融資產－流動淨額": 0,
      "應收帳款淨額": 1663074,
      "應收建造合約款": 2084699,
      "其他應收款淨額": 84537,
      "本期所得稅資產": 12436,
      "存貨": 908592,
      "預付款項": 312352,
      "其他流動資產": 1156462,
      "流動資產合計": 7137789,
      "非流動資產": null,
      "備供出售金融資產－非流動淨額": 82383,
      "採用權益法之投資淨額": 43309,
      "不動產、廠房及設備": 883707,
      "投資性不動產淨額": 189707,
      "遞延所得稅資產": 44676,
      "其他非流動資產": 228183,
      "非流動資產合計": 1471965,
      "資產總計": 8609754,
      "流動負債": null,
      "短期借款": 1433898,
      "應付短期票券": 0,
      "應付票據": 503996,
      "應付帳款": 1211846,
      "應付建造合約款": 153634,
      "其他應付款": 15527,
      "本期所得稅負債": 0,
      "負債準備－流動": 10011,
      "其他流動負債": 869747,
      "流動負債合計": 4198659,
      "非流動負債": null,
      "長期借款": 121803,
      "負債準備－非流動": 45497,
      "遞延所得稅負債": 21697,
      "其他非流動負債": 102378,
      "非流動負債合計": 291375,
      "負債總計": 4490034,
      "歸屬於母公司業主之權益": null,
      "股本": null,
      "普通股股本": 3475274,
      "股本合計": 3475274,
      "資本公積": null,
      "資本公積－發行溢價": 310362,
      "資本公積合計": 310362,
      "保留盈餘": null,
      "法定盈餘公積": 218565,
      "特別盈餘公積": 1872,
      "未分配盈餘（或待彌補虧損）": 2442,
      "保留盈餘合計": 222879,
      "其他權益": null,
      "國外營運機構財務報表換算之兌換差額": 39346,
      "備供出售金融資產未實現損益": 24154,
      "其他權益合計": 63500,
      "歸屬於母公司業主之權益合計": 4072015,
      "非控制權益": 47705,
      "權益總計": 4119720,
      "負債及權益總計": 8609754,
      "待註銷股本股數（單位：股）": 0,
      "預收股款（權益項下）之約當發行股數（單位：股）": 0,
      "母公司暨子公司所持有之母公司庫藏股股數（單位：股）": 0
   }
}