{
   "field": [
      "Season",
      "流動資產",
      "現金及約當現金",
      "透過損益按公允價值衡量之金融資產－流動",
      "按攤銷後成本衡量之金融資產－流動",
      "合約資產－流動",
      "應收票據淨額",
      "應收帳款淨額",
      "應收帳款－關係人淨額",
      "其他應收款淨額",
      "其他應收款－關係人淨額",
      "存貨",
      "待出售非流動資產（或處分群組）淨額",
      "其他流動資產",
      "流動資產合計",
      "非流動資產",
      "透過損益按公允價值衡量之金融資產－非流動",
      "透過其他綜合損益按公允價值衡量之金融資產－非流動",
      "按攤銷後成本衡量之金融資產－非流動",
      "採用權益法之投資",
      "不動產、廠房及設備",
      "使用權資產",
      "投資性不動產淨額",
      "無形資產",
      "遞延所得稅資產",
      "其他非流動資產",
      "非流動資產合計",
      "資產總額",
      "流動負債",
      "短期借款",
      "透過損益按公允價值衡量之金融負債－流動",
      "應付票據",
      "應付帳款",
      "應付帳款－關係人",
      "其他應付款",
      "其他應付款項－關係人",
      "本期所得稅負債",
      "負債準備－流動",
      "與待出售非流動資產直接相關（或處分群組）之負債",
      "租賃負債－流動",
      "其他流動負債",
      "流動負債合計",
      "非流動負債",
      "遞延所得稅負債",
      "租賃負債－非流動",
      "其他非流動負債",
      "非流動負債合計",
      "負債總額",
      "歸屬於母公司業主之權益",
      "股本",
      "普通股股本",
      "股本合計",
      "資本公積",
      "資本公積－發行溢價",
      "資本公積－庫藏股票交易",
      "資本公積-認列對子公司所有權權益變動數",
      "資本公積－採用權益法認列關聯企業及合資股權淨值之變動數",
      "資本公積－合併溢額",
      "資本公積合計",
      "保留盈餘",
      "法定盈餘公積",
      "特別盈餘公積",
      "未分配盈餘（或待彌補虧損）",
      "保留盈餘合計",
      "其他權益",
      "國外營運機構財務報表換算之兌換差額",
      "透過其他綜合損益按公允價值衡量之金融資產未實現評價損益",
      "避險工具之損益",
      "與待出售非流動資產（或處分群組）直接相關之權益",
      "其他權益合計",
      "庫藏股票",
      "歸屬於母公司業主之權益合計",
      "非控制權益",
      "權益總額",
      "負債及權益總計",
      "預收股款（權益項下）之約當發行股數（單位：股）",
      "母公司暨子公司所持有之母公司庫藏股股數（單位：股）"
   ],
   "data": {
      "Season": "2020/1",
      "流動資產": null,
      "現金及約當現金": 72491106,
      "透過損益按公允價值衡量之金融資產－流動": 318930,
      "按攤銷後成本衡量之金融資產－流動": 129210,
      "合約資產－流動": 2457232,
      "應收票據淨額": 340130,
      "應收帳款淨額": 27622224,
      "應收帳款－關係人淨額": 73698,
      "其他應收款淨額": 2527577,
      "其他應收款－關係人淨額": 12169,
      "存貨": 21269138,
      "待出售非流動資產（或處分群組）淨額": 6608485,
      "其他流動資產": 2078163,
      "流動資產合計": 135928062,
      "非流動資產": null,
      "透過損益按公允價值衡量之金融資產－非流動": 153524,
      "透過其他綜合損益按公允價值衡量之金融資產－非流動": 1487482,
      "按攤銷後成本衡量之金融資產－非流動": 361510,
      "採用權益法之投資": 5127827,
      "不動產、廠房及設備": 18507421,
      "使用權資產": 1398340,
      "投資性不動產淨額": 1261212,
      "無形資產": 5923019,
      "遞延所得稅資產": 4435813,
      "其他非流動資產": 539974,
      "非流動資產合計": 39196122,
      "資產總額": 175124184,
      "流動負債": null,
      "短期借款": 31945905,
      "透過損益按公允價值衡量之金融負債－流動": 313149,
      "應付票據": 15732,
      "應付帳款": 35615292,
      "應付帳款－關係人": 526628,
      "其他應付款": 24694580,
      "其他應付款項－關係人": 6127,
      "本期所得稅負債": 5553416,
      "負債準備－流動": 1055656,
      "與待出售非流動資產直接相關（或處分群組）之負債": 2639035,
      "租賃負債－流動": 267242,
      "其他流動負債": 2374522,
      "流動負債合計": 105007284,
      "非流動負債": null,
      "遞延所得稅負債": 1604962,
      "租賃負債－非流動": 524551,
      "其他非流動負債": 211550,
      "非流動負債合計": 2341063,
      "負債總額": 107348347,
      "歸屬於母公司業主之權益": null,
      "股本": null,
      "普通股股本": 23508670,
      "股本合計": 23508670,
      "資本公積": null,
      "資本公積－發行溢價": 10933950,
      "資本公積－庫藏股票交易": 548884,
      "資本公積-認列對子公司所有權權益變動數": 46706,
      "資本公積－採用權益法認列關聯企業及合資股權淨值之變動數": 258956,
      "資本公積－合併溢額": 10015194,
      "資本公積合計": 21803690,
      "保留盈餘": null,
      "法定盈餘公積": 13789554,
      "特別盈餘公積": 4732075,
      "未分配盈餘（或待彌補虧損）": 8653652,
      "保留盈餘合計": 27175281,
      "其他權益": null,
      "國外營運機構財務報表換算之兌換差額": -4984174,
      "透過其他綜合損益按公允價值衡量之金融資產未實現評價損益": -356369,
      "避險工具之損益": -93,
      "與待出售非流動資產（或處分群組）直接相關之權益": -13586,
      "其他權益合計": -5354222,
      "庫藏股票": -1271314,
      "歸屬於母公司業主之權益合計": 65862105,
      "非控制權益": 1913732,
      "權益總額": 67775837,
      "負債及權益總計": 175124184,
      "預收股款（權益項下）之約當發行股數（單位：股）": 0,
      "母公司暨子公司所持有之母公司庫藏股股數（單位：股）": 27303500
   }
}