{
   "field": [
      "Season",
      "流動資產",
      "現金及約當現金",
      "透過損益按公允價值衡量之金融資產－流動",
      "備供出售金融資產－流動淨額",
      "應收票據淨額",
      "應收帳款淨額",
      "應收帳款－關係人淨額",
      "其他應收款淨額",
      "其他應收款－關係人淨額",
      "存貨",
      "待出售非流動資產（淨額）",
      "其他流動資產",
      "流動資產合計",
      "非流動資產",
      "備供出售金融資產－非流動淨額",
      "不動產、廠房及設備",
      "投資性不動產淨額",
      "無形資產",
      "遞延所得稅資產",
      "其他非流動資產",
      "非流動資產合計",
      "資產總計",
      "流動負債",
      "短期借款",
      "應付短期票券",
      "透過損益按公允價值衡量之金融負債－流動",
      "應付票據",
      "應付帳款",
      "應付帳款－關係人",
      "其他應付款",
      "其他應付款項－關係人",
      "本期所得稅負債",
      "與待出售非流動資產直接相關之負債",
      "其他流動負債",
      "流動負債合計",
      "非流動負債",
      "應付公司債",
      "遞延所得稅負債",
      "其他非流動負債",
      "非流動負債合計",
      "負債總計",
      "歸屬於母公司業主之權益",
      "股本",
      "普通股股本",
      "股本合計",
      "資本公積",
      "資本公積合計",
      "保留盈餘",
      "法定盈餘公積",
      "未分配盈餘（或待彌補虧損）",
      "保留盈餘合計",
      "其他權益",
      "其他權益合計",
      "庫藏股票",
      "歸屬於母公司業主之權益合計",
      "非控制權益",
      "權益總計",
      "負債及權益總計",
      "待註銷股本股數（單位：股）",
      "預收股款（權益項下）之約當發行股數（單位：股）",
      "母公司暨子公司所持有之母公司庫藏股股數（單位：股）"
   ],
   "data": {
      "Season": "2015/3",
      "流動資產": null,
      "現金及約當現金": 1174935,
      "透過損益按公允價值衡量之金融資產－流動": 0,
      "備供出售金融資產－流動淨額": 181972,
      "應收票據淨額": 134963,
      "應收帳款淨額": 1648041,
      "應收帳款－關係人淨額": 17344,
      "其他應收款淨額": 8504,
      "其他應收款－關係人淨額": 982,
      "存貨": 982284,
      "待出售非流動資產（淨額）": 0,
      "其他流動資產": 650543,
      "流動資產合計": 4799568,
      "非流動資產": null,
      "備供出售金融資產－非流動淨額": 24594,
      "不動產、廠房及設備": 1255305,
      "投資性不動產淨額": 9059,
      "無形資產": 1520,
      "遞延所得稅資產": 35815,
      "其他非流動資產": 247242,
      "非流動資產合計": 1573535,
      "資產總計": 6373103,
      "流動負債": null,
      "短期借款": 256717,
      "應付短期票券": 49937,
      "透過損益按公允價值衡量之金融負債－流動": 0,
      "應付票據": 3564,
      "應付帳款": 272842,
      "應付帳款－關係人": 284336,
      "其他應付款": 257844,
      "其他應付款項－關係人": 40973,
      "本期所得稅負債": 71707,
      "與待出售非流動資產直接相關之負債": 0,
      "其他流動負債": 49378,
      "流動負債合計": 1287298,
      "非流動負債": null,
      "應付公司債": 0,
      "遞延所得稅負債": 399568,
      "其他非流動負債": 29176,
      "非流動負債合計": 428744,
      "負債總計": 1716042,
      "歸屬於母公司業主之權益": null,
      "股本": null,
      "普通股股本": 1274697,
      "股本合計": 1274697,
      "資本公積": null,
      "資本公積合計": 332100,
      "保留盈餘": null,
      "法定盈餘公積": 542664,
      "未分配盈餘（或待彌補虧損）": 2004262,
      "保留盈餘合計": 2546926,
      "其他權益": null,
      "其他權益合計": 350959,
      "庫藏股票": 0,
      "歸屬於母公司業主之權益合計": 4504682,
      "非控制權益": 152379,
      "權益總計": 4657061,
      "負債及權益總計": 6373103,
      "待註銷股本股數（單位：股）": 0,
      "預收股款（權益項下）之約當發行股數（單位：股）": 0,
      "母公司暨子公司所持有之母公司庫藏股股數（單位：股）": 0
   }
}