{
   "field": [
      "Season",
      "流動資產",
      "現金及約當現金",
      "應收票據淨額",
      "應收帳款淨額",
      "其他應收款淨額",
      "本期所得稅資產",
      "存貨",
      "預付款項",
      "其他流動資產",
      "流動資產合計",
      "非流動資產",
      "不動產、廠房及設備",
      "遞延所得稅資產",
      "其他非流動資產",
      "非流動資產合計",
      "資產總計",
      "流動負債",
      "應付帳款",
      "其他應付款",
      "其他流動負債",
      "流動負債合計",
      "非流動負債",
      "長期借款",
      "遞延所得稅負債",
      "其他非流動負債",
      "非流動負債合計",
      "負債總計",
      "股本",
      "普通股股本",
      "股本合計",
      "資本公積",
      "資本公積－發行溢價",
      "資本公積－限制員工權利股票",
      "資本公積合計",
      "保留盈餘",
      "未分配盈餘（或待彌補虧損）",
      "保留盈餘合計",
      "其他權益",
      "其他權益－其他",
      "其他權益合計",
      "權益總計",
      "負債及權益總計",
      "待註銷股本股數（單位：股）",
      "預收股款（權益項下）之約當發行股數（單位：股）",
      "母公司暨子公司所持有之母公司庫藏股股數（單位：股）"
   ],
   "data": {
      "Season": "2016/4",
      "流動資產": null,
      "現金及約當現金": 876291,
      "應收票據淨額": 0,
      "應收帳款淨額": 71494,
      "其他應收款淨額": 1134,
      "本期所得稅資產": 660,
      "存貨": 138045,
      "預付款項": 44934,
      "其他流動資產": 173,
      "流動資產合計": 1132731,
      "非流動資產": null,
      "不動產、廠房及設備": 2711662,
      "遞延所得稅資產": 5814,
      "其他非流動資產": 62960,
      "非流動資產合計": 2780436,
      "資產總計": 3913167,
      "流動負債": null,
      "應付帳款": 86645,
      "其他應付款": 79347,
      "其他流動負債": 26756,
      "流動負債合計": 192748,
      "非流動負債": null,
      "長期借款": 42917,
      "遞延所得稅負債": 12,
      "其他非流動負債": 4804,
      "非流動負債合計": 47733,
      "負債總計": 240481,
      "股本": null,
      "普通股股本": 3496268,
      "股本合計": 3496268,
      "資本公積": null,
      "資本公積－發行溢價": 910062,
      "資本公積－限制員工權利股票": 0,
      "資本公積合計": 910062,
      "保留盈餘": null,
      "未分配盈餘（或待彌補虧損）": -733644,
      "保留盈餘合計": -733644,
      "其他權益": null,
      "其他權益－其他": 0,
      "其他權益合計": 0,
      "權益總計": 3672686,
      "負債及權益總計": 3913167,
      "待註銷股本股數（單位：股）": 0,
      "預收股款（權益項下）之約當發行股數（單位：股）": 0,
      "母公司暨子公司所持有之母公司庫藏股股數（單位：股）": 0
   }
}