{
   "field": [
      "Season",
      "流動資產",
      "現金及約當現金",
      "按攤銷後成本衡量之金融資產－流動",
      "應收票據淨額",
      "應收帳款淨額",
      "應收帳款－關係人淨額",
      "其他應收款淨額",
      "存貨",
      "其他流動資產",
      "流動資產合計",
      "非流動資產",
      "透過其他綜合損益按公允價值衡量之金融資產－非流動",
      "按攤銷後成本衡量之金融資產－非流動",
      "採用權益法之投資",
      "不動產、廠房及設備",
      "使用權資產",
      "遞延所得稅資產",
      "其他非流動資產",
      "非流動資產合計",
      "資產總額",
      "流動負債",
      "短期借款",
      "應付短期票券",
      "合約負債－流動",
      "應付票據",
      "應付帳款",
      "其他應付款",
      "本期所得稅負債",
      "租賃負債－流動",
      "其他流動負債",
      "流動負債合計",
      "非流動負債",
      "長期借款",
      "遞延所得稅負債",
      "租賃負債－非流動",
      "其他非流動負債",
      "非流動負債合計",
      "負債總額",
      "歸屬於母公司業主之權益",
      "股本",
      "普通股股本",
      "股本合計",
      "資本公積",
      "資本公積－發行溢價",
      "資本公積－處分資產增益",
      "資本公積－限制員工權利股票",
      "資本公積合計",
      "保留盈餘",
      "法定盈餘公積",
      "特別盈餘公積",
      "未分配盈餘（或待彌補虧損）",
      "保留盈餘合計",
      "其他權益",
      "其他權益－其他",
      "其他權益合計",
      "庫藏股票",
      "歸屬於母公司業主之權益合計",
      "權益總額",
      "負債及權益總計",
      "預收股款（權益項下）之約當發行股數（單位：股）",
      "母公司暨子公司所持有之母公司庫藏股股數（單位：股）"
   ],
   "data": {
      "Season": "2019/4",
      "流動資產": null,
      "現金及約當現金": 366933,
      "按攤銷後成本衡量之金融資產－流動": 131127,
      "應收票據淨額": 26650,
      "應收帳款淨額": 346310,
      "應收帳款－關係人淨額": 7322,
      "其他應收款淨額": 11342,
      "存貨": 255804,
      "其他流動資產": 59310,
      "流動資產合計": 1204798,
      "非流動資產": null,
      "透過其他綜合損益按公允價值衡量之金融資產－非流動": 2640,
      "按攤銷後成本衡量之金融資產－非流動": 153896,
      "採用權益法之投資": 5887,
      "不動產、廠房及設備": 829526,
      "使用權資產": 64711,
      "遞延所得稅資產": 70657,
      "其他非流動資產": 63783,
      "非流動資產合計": 1191100,
      "資產總額": 2395898,
      "流動負債": null,
      "短期借款": 523987,
      "應付短期票券": 30000,
      "合約負債－流動": 4685,
      "應付票據": 13814,
      "應付帳款": 242439,
      "其他應付款": 125867,
      "本期所得稅負債": 1890,
      "租賃負債－流動": 28795,
      "其他流動負債": 79585,
      "流動負債合計": 1051062,
      "非流動負債": null,
      "長期借款": 118800,
      "遞延所得稅負債": 1173,
      "租賃負債－非流動": 25019,
      "其他非流動負債": 49025,
      "非流動負債合計": 194017,
      "負債總額": 1245079,
      "歸屬於母公司業主之權益": null,
      "股本": null,
      "普通股股本": 628990,
      "股本合計": 628990,
      "資本公積": null,
      "資本公積－發行溢價": 342675,
      "資本公積－處分資產增益": 255,
      "資本公積－限制員工權利股票": 3561,
      "資本公積合計": 346491,
      "保留盈餘": null,
      "法定盈餘公積": 61149,
      "特別盈餘公積": 25389,
      "未分配盈餘（或待彌補虧損）": 139504,
      "保留盈餘合計": 226042,
      "其他權益": null,
      "其他權益－其他": -45245,
      "其他權益合計": -45245,
      "庫藏股票": -5459,
      "歸屬於母公司業主之權益合計": 1150819,
      "權益總額": 1150819,
      "負債及權益總計": 2395898,
      "預收股款（權益項下）之約當發行股數（單位：股）": 0,
      "母公司暨子公司所持有之母公司庫藏股股數（單位：股）": 245000
   }
}