{
   "field": [
      "Season",
      "流動資產",
      "現金及約當現金",
      "透過損益按公允價值衡量之金融資產－流動",
      "備供出售金融資產－流動淨額",
      "無活絡市場之債務工具投資－流動淨額",
      "應收票據淨額",
      "應收帳款淨額",
      "應收帳款－關係人淨額",
      "其他應收款淨額",
      "其他應收款－關係人淨額",
      "存貨",
      "預付款項",
      "其他流動資產",
      "流動資產合計",
      "非流動資產",
      "備供出售金融資產－非流動淨額",
      "無活絡市場之債務工具投資－非流動淨額",
      "採用權益法之投資淨額",
      "不動產、廠房及設備",
      "無形資產",
      "遞延所得稅資產",
      "其他非流動資產",
      "非流動資產合計",
      "資產總計",
      "流動負債",
      "短期借款",
      "應付短期票券",
      "透過損益按公允價值衡量之金融負債－流動",
      "應付票據",
      "應付帳款",
      "應付帳款－關係人",
      "其他應付款",
      "其他應付款項－關係人",
      "本期所得稅負債",
      "其他流動負債",
      "流動負債合計",
      "非流動負債",
      "長期借款",
      "遞延所得稅負債",
      "其他非流動負債",
      "非流動負債合計",
      "負債總計",
      "歸屬於母公司業主之權益",
      "股本",
      "普通股股本",
      "預收股本",
      "股本合計",
      "資本公積",
      "資本公積－發行溢價",
      "資本公積－採用權益法認列關聯企業及合資股權淨值之變動數",
      "資本公積－員工認股權",
      "資本公積合計",
      "保留盈餘",
      "法定盈餘公積",
      "特別盈餘公積",
      "未分配盈餘（或待彌補虧損）",
      "保留盈餘合計",
      "其他權益",
      "國外營運機構財務報表換算之兌換差額",
      "備供出售金融資產未實現損益",
      "其他權益合計",
      "庫藏股票",
      "歸屬於母公司業主之權益合計",
      "非控制權益",
      "權益總計",
      "負債及權益總計",
      "待註銷股本股數（單位：股）",
      "預收股款（權益項下）之約當發行股數（單位：股）",
      "母公司暨子公司所持有之母公司庫藏股股數（單位：股）"
   ],
   "data": {
      "Season": "2016/2",
      "流動資產": null,
      "現金及約當現金": 5163233,
      "透過損益按公允價值衡量之金融資產－流動": 2832,
      "備供出售金融資產－流動淨額": 0,
      "無活絡市場之債務工具投資－流動淨額": 7555675,
      "應收票據淨額": 431334,
      "應收帳款淨額": 8210510,
      "應收帳款－關係人淨額": 1568,
      "其他應收款淨額": 223917,
      "其他應收款－關係人淨額": 254295,
      "存貨": 4705645,
      "預付款項": 188862,
      "其他流動資產": 88969,
      "流動資產合計": 26826840,
      "非流動資產": null,
      "備供出售金融資產－非流動淨額": 2153991,
      "無活絡市場之債務工具投資－非流動淨額": 50000,
      "採用權益法之投資淨額": 2508538,
      "不動產、廠房及設備": 13469193,
      "無形資產": 2379436,
      "遞延所得稅資產": 754380,
      "其他非流動資產": 306261,
      "非流動資產合計": 21621799,
      "資產總計": 48448639,
      "流動負債": null,
      "短期借款": 11417624,
      "應付短期票券": 499924,
      "透過損益按公允價值衡量之金融負債－流動": 40800,
      "應付票據": 7558,
      "應付帳款": 4174883,
      "應付帳款－關係人": 719719,
      "其他應付款": 5550334,
      "其他應付款項－關係人": 0,
      "本期所得稅負債": 636371,
      "其他流動負債": 270558,
      "流動負債合計": 23317771,
      "非流動負債": null,
      "長期借款": 1900000,
      "遞延所得稅負債": 20081,
      "其他非流動負債": 319386,
      "非流動負債合計": 2239467,
      "負債總計": 25557238,
      "歸屬於母公司業主之權益": null,
      "股本": null,
      "普通股股本": 5142550,
      "預收股本": 3210,
      "股本合計": 5145760,
      "資本公積": null,
      "資本公積－發行溢價": 177861,
      "資本公積－採用權益法認列關聯企業及合資股權淨值之變動數": 61795,
      "資本公積－員工認股權": 29509,
      "資本公積合計": 269165,
      "保留盈餘": null,
      "法定盈餘公積": 2155454,
      "特別盈餘公積": 437595,
      "未分配盈餘（或待彌補虧損）": 15475818,
      "保留盈餘合計": 18068867,
      "其他權益": null,
      "國外營運機構財務報表換算之兌換差額": -68303,
      "備供出售金融資產未實現損益": -656203,
      "其他權益合計": -724506,
      "庫藏股票": 0,
      "歸屬於母公司業主之權益合計": 22759286,
      "非控制權益": 132115,
      "權益總計": 22891401,
      "負債及權益總計": 48448639,
      "待註銷股本股數（單位：股）": 0,
      "預收股款（權益項下）之約當發行股數（單位：股）": 321000,
      "母公司暨子公司所持有之母公司庫藏股股數（單位：股）": 0
   }
}