{
   "field": [
      "Season",
      "流動資產",
      "現金及約當現金",
      "按攤銷後成本衡量之金融資產－流動",
      "應收票據淨額",
      "應收帳款淨額",
      "存貨",
      "預付款項",
      "其他流動資產",
      "流動資產合計",
      "非流動資產",
      "透過其他綜合損益按公允價值衡量之金融資產－非流動",
      "不動產、廠房及設備",
      "使用權資產",
      "投資性不動產淨額",
      "無形資產",
      "遞延所得稅資產",
      "其他非流動資產",
      "非流動資產合計",
      "資產總額",
      "流動負債",
      "短期借款",
      "合約負債－流動",
      "應付帳款",
      "其他應付款",
      "本期所得稅負債",
      "租賃負債－流動",
      "其他流動負債",
      "流動負債合計",
      "非流動負債",
      "遞延所得稅負債",
      "租賃負債－非流動",
      "其他非流動負債",
      "非流動負債合計",
      "負債總額",
      "歸屬於母公司業主之權益",
      "股本",
      "普通股股本",
      "股本合計",
      "資本公積",
      "資本公積合計",
      "保留盈餘",
      "法定盈餘公積",
      "特別盈餘公積",
      "未分配盈餘（或待彌補虧損）",
      "保留盈餘合計",
      "其他權益",
      "其他權益合計",
      "庫藏股票",
      "歸屬於母公司業主之權益合計",
      "權益總額",
      "負債及權益總計",
      "待註銷股本股數（單位：股）",
      "預收股款（權益項下）之約當發行股數（單位：股）",
      "母公司暨子公司所持有之母公司庫藏股股數（單位：股）"
   ],
   "data": {
      "Season": "2022/3",
      "流動資產": null,
      "現金及約當現金": 1068255,
      "按攤銷後成本衡量之金融資產－流動": 9544,
      "應收票據淨額": 77655,
      "應收帳款淨額": 829032,
      "存貨": 1392624,
      "預付款項": 101615,
      "其他流動資產": 5684,
      "流動資產合計": 3484409,
      "非流動資產": null,
      "透過其他綜合損益按公允價值衡量之金融資產－非流動": 25575,
      "不動產、廠房及設備": 997399,
      "使用權資產": 41724,
      "投資性不動產淨額": 198761,
      "無形資產": 27045,
      "遞延所得稅資產": 83821,
      "其他非流動資產": 6982,
      "非流動資產合計": 1381307,
      "資產總額": 4865716,
      "流動負債": null,
      "短期借款": 258752,
      "合約負債－流動": 24483,
      "應付帳款": 305623,
      "其他應付款": 136736,
      "本期所得稅負債": 59989,
      "租賃負債－流動": 1091,
      "其他流動負債": 1146,
      "流動負債合計": 787820,
      "非流動負債": null,
      "遞延所得稅負債": 269425,
      "租賃負債－非流動": 1079,
      "其他非流動負債": 19686,
      "非流動負債合計": 290190,
      "負債總額": 1078010,
      "歸屬於母公司業主之權益": null,
      "股本": null,
      "普通股股本": 1836081,
      "股本合計": 1836081,
      "資本公積": null,
      "資本公積合計": 199595,
      "保留盈餘": null,
      "法定盈餘公積": 734810,
      "特別盈餘公積": 202052,
      "未分配盈餘（或待彌補虧損）": 979837,
      "保留盈餘合計": 1916699,
      "其他權益": null,
      "其他權益合計": -140610,
      "庫藏股票": -24059,
      "歸屬於母公司業主之權益合計": 3787706,
      "權益總額": 3787706,
      "負債及權益總計": 4865716,
      "待註銷股本股數（單位：股）": 0,
      "預收股款（權益項下）之約當發行股數（單位：股）": 0,
      "母公司暨子公司所持有之母公司庫藏股股數（單位：股）": 1500000
   }
}