{
   "field": [
      "Season",
      "流動資產",
      "現金及約當現金",
      "透過損益按公允價值衡量之金融資產－流動",
      "按攤銷後成本衡量之金融資產－流動",
      "應收票據淨額",
      "應收帳款淨額",
      "應收帳款－關係人淨額",
      "其他應收款淨額",
      "其他應收款－關係人淨額",
      "本期所得稅資產",
      "存貨",
      "其他流動資產",
      "流動資產合計",
      "非流動資產",
      "透過其他綜合損益按公允價值衡量之金融資產－非流動",
      "採用權益法之投資",
      "不動產、廠房及設備",
      "使用權資產",
      "無形資產",
      "遞延所得稅資產",
      "其他非流動資產",
      "非流動資產合計",
      "資產總額",
      "流動負債",
      "短期借款",
      "合約負債－流動",
      "應付帳款",
      "應付帳款－關係人",
      "其他應付款",
      "其他應付款項－關係人",
      "本期所得稅負債",
      "租賃負債－流動",
      "其他流動負債",
      "流動負債合計",
      "非流動負債",
      "長期借款",
      "遞延所得稅負債",
      "租賃負債－非流動",
      "其他非流動負債",
      "非流動負債合計",
      "負債總額",
      "歸屬於母公司業主之權益",
      "股本",
      "普通股股本",
      "股本合計",
      "資本公積",
      "資本公積合計",
      "保留盈餘",
      "法定盈餘公積",
      "特別盈餘公積",
      "未分配盈餘（或待彌補虧損）",
      "保留盈餘合計",
      "其他權益",
      "國外營運機構財務報表換算之兌換差額",
      "透過其他綜合損益按公允價值衡量之金融資產未實現評價損益",
      "其他權益合計",
      "歸屬於母公司業主之權益合計",
      "非控制權益",
      "權益總額",
      "負債及權益總計",
      "待註銷股本股數（單位：股）",
      "預收股款（權益項下）之約當發行股數（單位：股）",
      "母公司暨子公司所持有之母公司庫藏股股數（單位：股）"
   ],
   "data": {
      "Season": "2021/1",
      "流動資產": null,
      "現金及約當現金": 3062609,
      "透過損益按公允價值衡量之金融資產－流動": 1286730,
      "按攤銷後成本衡量之金融資產－流動": 22672,
      "應收票據淨額": 38332,
      "應收帳款淨額": 1176622,
      "應收帳款－關係人淨額": 0,
      "其他應收款淨額": 45804,
      "其他應收款－關係人淨額": 0,
      "本期所得稅資產": 48014,
      "存貨": 874532,
      "其他流動資產": 164513,
      "流動資產合計": 6719828,
      "非流動資產": null,
      "透過其他綜合損益按公允價值衡量之金融資產－非流動": 231524,
      "採用權益法之投資": 148829,
      "不動產、廠房及設備": 1188683,
      "使用權資產": 152007,
      "無形資產": 3094,
      "遞延所得稅資產": 19750,
      "其他非流動資產": 43381,
      "非流動資產合計": 1787268,
      "資產總額": 8507096,
      "流動負債": null,
      "短期借款": 1272207,
      "合約負債－流動": 12766,
      "應付帳款": 543147,
      "應付帳款－關係人": 2706,
      "其他應付款": 337914,
      "其他應付款項－關係人": 1874,
      "本期所得稅負債": 46568,
      "租賃負債－流動": 16763,
      "其他流動負債": 40141,
      "流動負債合計": 2274086,
      "非流動負債": null,
      "長期借款": 52708,
      "遞延所得稅負債": 585030,
      "租賃負債－非流動": 78940,
      "其他非流動負債": 78002,
      "非流動負債合計": 794680,
      "負債總額": 3068766,
      "歸屬於母公司業主之權益": null,
      "股本": null,
      "普通股股本": 1849683,
      "股本合計": 1849683,
      "資本公積": null,
      "資本公積合計": 433908,
      "保留盈餘": null,
      "法定盈餘公積": 798682,
      "特別盈餘公積": 284690,
      "未分配盈餘（或待彌補虧損）": 1639821,
      "保留盈餘合計": 2723193,
      "其他權益": null,
      "國外營運機構財務報表換算之兌換差額": -404406,
      "透過其他綜合損益按公允價值衡量之金融資產未實現評價損益": 206082,
      "其他權益合計": -198324,
      "歸屬於母公司業主之權益合計": 4808460,
      "非控制權益": 629870,
      "權益總額": 5438330,
      "負債及權益總計": 8507096,
      "待註銷股本股數（單位：股）": 0,
      "預收股款（權益項下）之約當發行股數（單位：股）": 0,
      "母公司暨子公司所持有之母公司庫藏股股數（單位：股）": 0
   }
}