{
   "field": [
      "Season",
      "流動資產",
      "現金及約當現金",
      "透過損益按公允價值衡量之金融資產－流動",
      "應收票據淨額",
      "應收票據－關係人淨額",
      "應收帳款淨額",
      "應收帳款－關係人淨額",
      "其他應收款淨額",
      "其他應收款－關係人淨額",
      "本期所得稅資產",
      "存貨",
      "預付款項",
      "其他流動資產",
      "流動資產合計",
      "非流動資產",
      "不動產、廠房及設備",
      "使用權資產",
      "無形資產",
      "遞延所得稅資產",
      "其他非流動資產",
      "非流動資產合計",
      "資產總額",
      "流動負債",
      "短期借款",
      "透過損益按公允價值衡量之金融負債－流動",
      "應付票據",
      "應付票據－關係人",
      "其他應付款",
      "本期所得稅負債",
      "租賃負債－流動",
      "其他流動負債",
      "流動負債合計",
      "非流動負債",
      "長期借款",
      "遞延所得稅負債",
      "租賃負債－非流動",
      "其他非流動負債",
      "非流動負債合計",
      "負債總額",
      "歸屬於母公司業主之權益",
      "股本",
      "普通股股本",
      "股本合計",
      "資本公積",
      "資本公積合計",
      "保留盈餘",
      "保留盈餘合計",
      "其他權益",
      "其他權益合計",
      "庫藏股票",
      "歸屬於母公司業主之權益合計",
      "權益總額",
      "負債及權益總計",
      "預收股款（權益項下）之約當發行股數（單位：股）",
      "母公司暨子公司所持有之母公司庫藏股股數（單位：股）"
   ],
   "data": {
      "Season": "2022/4",
      "流動資產": null,
      "現金及約當現金": 539333,
      "透過損益按公允價值衡量之金融資產－流動": 16471,
      "應收票據淨額": 600,
      "應收票據－關係人淨額": 0,
      "應收帳款淨額": 1654973,
      "應收帳款－關係人淨額": 149890,
      "其他應收款淨額": 291520,
      "其他應收款－關係人淨額": 8094,
      "本期所得稅資產": 0,
      "存貨": 959597,
      "預付款項": 124503,
      "其他流動資產": 244942,
      "流動資產合計": 3989923,
      "非流動資產": null,
      "不動產、廠房及設備": 2321655,
      "使用權資產": 580748,
      "無形資產": 116382,
      "遞延所得稅資產": 37330,
      "其他非流動資產": 97547,
      "非流動資產合計": 3153662,
      "資產總額": 7143585,
      "流動負債": null,
      "短期借款": 327592,
      "透過損益按公允價值衡量之金融負債－流動": 51,
      "應付票據": 676067,
      "應付票據－關係人": 0,
      "其他應付款": 243071,
      "本期所得稅負債": 120603,
      "租賃負債－流動": 23187,
      "其他流動負債": 222390,
      "流動負債合計": 1612961,
      "非流動負債": null,
      "長期借款": 3170816,
      "遞延所得稅負債": 4755,
      "租賃負債－非流動": 74943,
      "其他非流動負債": 1412,
      "非流動負債合計": 3251926,
      "負債總額": 4864887,
      "歸屬於母公司業主之權益": null,
      "股本": null,
      "普通股股本": 1696233,
      "股本合計": 1696233,
      "資本公積": null,
      "資本公積合計": 13030,
      "保留盈餘": null,
      "保留盈餘合計": 652769,
      "其他權益": null,
      "其他權益合計": -63404,
      "庫藏股票": -19930,
      "歸屬於母公司業主之權益合計": 2278698,
      "權益總額": 2278698,
      "負債及權益總計": 7143585,
      "預收股款（權益項下）之約當發行股數（單位：股）": 0,
      "母公司暨子公司所持有之母公司庫藏股股數（單位：股）": 1000000
   }
}