{
   "field": [
      "Season",
      "流動資產",
      "現金及約當現金",
      "透過損益按公允價值衡量之金融資產－流動",
      "按攤銷後成本衡量之金融資產－流動",
      "應收票據淨額",
      "應收帳款淨額",
      "應收帳款－關係人淨額",
      "應收融資租賃款淨額",
      "存貨",
      "其他流動資產",
      "流動資產合計",
      "非流動資產",
      "透過損益按公允價值衡量之金融資產－非流動",
      "透過其他綜合損益按公允價值衡量之金融資產－非流動",
      "按攤銷後成本衡量之金融資產－非流動",
      "採用權益法之投資",
      "不動產、廠房及設備",
      "使用權資產",
      "投資性不動產淨額",
      "遞延所得稅資產",
      "其他非流動資產",
      "非流動資產合計",
      "資產總額",
      "流動負債",
      "短期借款",
      "應付短期票券",
      "透過損益按公允價值衡量之金融負債－流動",
      "應付票據",
      "應付帳款",
      "應付帳款－關係人",
      "其他應付款",
      "本期所得稅負債",
      "租賃負債－流動",
      "其他流動負債",
      "流動負債合計",
      "非流動負債",
      "長期借款",
      "遞延所得稅負債",
      "租賃負債－非流動",
      "其他非流動負債",
      "非流動負債合計",
      "負債總額",
      "歸屬於母公司業主之權益",
      "股本",
      "普通股股本",
      "股本合計",
      "資本公積",
      "資本公積合計",
      "保留盈餘",
      "法定盈餘公積",
      "特別盈餘公積",
      "未分配盈餘（或待彌補虧損）",
      "保留盈餘合計",
      "其他權益",
      "國外營運機構財務報表換算之兌換差額",
      "透過其他綜合損益按公允價值衡量之金融資產未實現評價損益",
      "其他權益合計",
      "庫藏股票",
      "歸屬於母公司業主之權益合計",
      "共同控制下前手權益",
      "非控制權益",
      "權益總額",
      "負債及權益總計",
      "待註銷股本股數（單位：股）",
      "預收股款（權益項下）之約當發行股數（單位：股）",
      "母公司暨子公司所持有之母公司庫藏股股數（單位：股）"
   ],
   "data": {
      "Season": "2019/3",
      "流動資產": null,
      "現金及約當現金": 1118549,
      "透過損益按公允價值衡量之金融資產－流動": 223372,
      "按攤銷後成本衡量之金融資產－流動": 6123,
      "應收票據淨額": 4084,
      "應收帳款淨額": 196590,
      "應收帳款－關係人淨額": 107,
      "應收融資租賃款淨額": 1990,
      "存貨": 70301,
      "其他流動資產": 102844,
      "流動資產合計": 1723960,
      "非流動資產": null,
      "透過損益按公允價值衡量之金融資產－非流動": 106076,
      "透過其他綜合損益按公允價值衡量之金融資產－非流動": 189005,
      "按攤銷後成本衡量之金融資產－非流動": 142715,
      "採用權益法之投資": 185612,
      "不動產、廠房及設備": 2601226,
      "使用權資產": 206768,
      "投資性不動產淨額": 152917,
      "遞延所得稅資產": 19553,
      "其他非流動資產": 86227,
      "非流動資產合計": 3690099,
      "資產總額": 5414059,
      "流動負債": null,
      "短期借款": 280328,
      "應付短期票券": 24467,
      "透過損益按公允價值衡量之金融負債－流動": 0,
      "應付票據": 60,
      "應付帳款": 69138,
      "應付帳款－關係人": 57773,
      "其他應付款": 169271,
      "本期所得稅負債": 4591,
      "租賃負債－流動": 27923,
      "其他流動負債": 305258,
      "流動負債合計": 938809,
      "非流動負債": null,
      "長期借款": 1618382,
      "遞延所得稅負債": 31022,
      "租賃負債－非流動": 194358,
      "其他非流動負債": 48591,
      "非流動負債合計": 1892353,
      "負債總額": 2831162,
      "歸屬於母公司業主之權益": null,
      "股本": null,
      "普通股股本": 1459845,
      "股本合計": 1459845,
      "資本公積": null,
      "資本公積合計": 520613,
      "保留盈餘": null,
      "法定盈餘公積": 41520,
      "特別盈餘公積": 42579,
      "未分配盈餘（或待彌補虧損）": 285518,
      "保留盈餘合計": 369617,
      "其他權益": null,
      "國外營運機構財務報表換算之兌換差額": 6098,
      "透過其他綜合損益按公允價值衡量之金融資產未實現評價損益": -57729,
      "其他權益合計": -51631,
      "庫藏股票": 0,
      "歸屬於母公司業主之權益合計": 2298444,
      "共同控制下前手權益": 0,
      "非控制權益": 284453,
      "權益總額": 2582897,
      "負債及權益總計": 5414059,
      "待註銷股本股數（單位：股）": 0,
      "預收股款（權益項下）之約當發行股數（單位：股）": 0,
      "母公司暨子公司所持有之母公司庫藏股股數（單位：股）": 0
   }
}