{
   "field": [
      "Season",
      "流動資產",
      "現金及約當現金",
      "透過損益按公允價值衡量之金融資產－流動",
      "透過其他綜合損益按公允價值衡量之金融資產－流動",
      "應收票據淨額",
      "應收帳款淨額",
      "應收帳款－關係人淨額",
      "其他應收款淨額",
      "其他應收款－關係人淨額",
      "本期所得稅資產",
      "存貨",
      "預付款項",
      "其他流動資產",
      "流動資產合計",
      "非流動資產",
      "透過其他綜合損益按公允價值衡量之金融資產－非流動",
      "採用權益法之投資",
      "不動產、廠房及設備",
      "使用權資產",
      "投資性不動產淨額",
      "無形資產",
      "遞延所得稅資產",
      "其他非流動資產",
      "非流動資產合計",
      "資產總額",
      "流動負債",
      "短期借款",
      "透過損益按公允價值衡量之金融負債－流動",
      "應付票據",
      "應付帳款",
      "其他應付款",
      "其他應付款項－關係人",
      "本期所得稅負債",
      "負債準備－流動",
      "租賃負債－流動",
      "其他流動負債",
      "流動負債合計",
      "非流動負債",
      "負債準備－非流動",
      "遞延所得稅負債",
      "租賃負債－非流動",
      "其他非流動負債",
      "非流動負債合計",
      "負債總額",
      "歸屬於母公司業主之權益",
      "股本",
      "普通股股本",
      "股本合計",
      "資本公積",
      "資本公積合計",
      "保留盈餘",
      "法定盈餘公積",
      "未分配盈餘（或待彌補虧損）",
      "保留盈餘合計",
      "其他權益",
      "其他權益合計",
      "歸屬於母公司業主之權益合計",
      "權益總額",
      "負債及權益總計",
      "預收股款（權益項下）之約當發行股數（單位：股）",
      "母公司暨子公司所持有之母公司庫藏股股數（單位：股）"
   ],
   "data": {
      "Season": "2023/4",
      "流動資產": null,
      "現金及約當現金": 580195,
      "透過損益按公允價值衡量之金融資產－流動": 32020,
      "透過其他綜合損益按公允價值衡量之金融資產－流動": 44045,
      "應收票據淨額": 308839,
      "應收帳款淨額": 737583,
      "應收帳款－關係人淨額": 0,
      "其他應收款淨額": 8388,
      "其他應收款－關係人淨額": 48,
      "本期所得稅資產": 2468,
      "存貨": 1420363,
      "預付款項": 127992,
      "其他流動資產": 66256,
      "流動資產合計": 3328197,
      "非流動資產": null,
      "透過其他綜合損益按公允價值衡量之金融資產－非流動": 849902,
      "採用權益法之投資": 233327,
      "不動產、廠房及設備": 1473914,
      "使用權資產": 240525,
      "投資性不動產淨額": 91643,
      "無形資產": 9925,
      "遞延所得稅資產": 76627,
      "其他非流動資產": 99512,
      "非流動資產合計": 3075375,
      "資產總額": 6403572,
      "流動負債": null,
      "短期借款": 357159,
      "透過損益按公允價值衡量之金融負債－流動": 624,
      "應付票據": 36565,
      "應付帳款": 468221,
      "其他應付款": 643160,
      "其他應付款項－關係人": 918,
      "本期所得稅負債": 52796,
      "負債準備－流動": 7972,
      "租賃負債－流動": 121722,
      "其他流動負債": 329315,
      "流動負債合計": 2018452,
      "非流動負債": null,
      "負債準備－非流動": 38448,
      "遞延所得稅負債": 21136,
      "租賃負債－非流動": 122277,
      "其他非流動負債": 11015,
      "非流動負債合計": 192876,
      "負債總額": 2211328,
      "歸屬於母公司業主之權益": null,
      "股本": null,
      "普通股股本": 730004,
      "股本合計": 730004,
      "資本公積": null,
      "資本公積合計": 825306,
      "保留盈餘": null,
      "法定盈餘公積": 733788,
      "未分配盈餘（或待彌補虧損）": 1901018,
      "保留盈餘合計": 2634806,
      "其他權益": null,
      "其他權益合計": 2128,
      "歸屬於母公司業主之權益合計": 4192244,
      "權益總額": 4192244,
      "負債及權益總計": 6403572,
      "預收股款（權益項下）之約當發行股數（單位：股）": 0,
      "母公司暨子公司所持有之母公司庫藏股股數（單位：股）": 0
   }
}