{
   "field": [
      "Season",
      "流動資產",
      "現金及約當現金",
      "按攤銷後成本衡量之金融資產－流動",
      "應收票據淨額",
      "應收帳款淨額",
      "其他應收款淨額",
      "存貨",
      "預付款項",
      "其他流動資產",
      "流動資產合計",
      "非流動資產",
      "不動產、廠房及設備",
      "使用權資產",
      "投資性不動產淨額",
      "其他非流動資產",
      "非流動資產合計",
      "資產總額",
      "流動負債",
      "短期借款",
      "應付帳款",
      "其他應付款",
      "其他流動負債",
      "流動負債合計",
      "非流動負債",
      "遞延所得稅負債",
      "其他非流動負債",
      "非流動負債合計",
      "負債總額",
      "歸屬於母公司業主之權益",
      "股本",
      "普通股股本",
      "股本合計",
      "資本公積",
      "資本公積合計",
      "保留盈餘",
      "法定盈餘公積",
      "特別盈餘公積",
      "未分配盈餘（或待彌補虧損）",
      "保留盈餘合計",
      "其他權益",
      "國外營運機構財務報表換算之兌換差額",
      "其他權益合計",
      "歸屬於母公司業主之權益合計",
      "權益總額",
      "負債及權益總計",
      "預收股款（權益項下）之約當發行股數（單位：股）",
      "母公司暨子公司所持有之母公司庫藏股股數（單位：股）"
   ],
   "data": {
      "Season": "2020/1",
      "流動資產": null,
      "現金及約當現金": 1220883,
      "按攤銷後成本衡量之金融資產－流動": 1278000,
      "應收票據淨額": 42628,
      "應收帳款淨額": 171065,
      "其他應收款淨額": 12963,
      "存貨": 222673,
      "預付款項": 18013,
      "其他流動資產": 0,
      "流動資產合計": 2966225,
      "非流動資產": null,
      "不動產、廠房及設備": 3221429,
      "使用權資產": 897891,
      "投資性不動產淨額": 136372,
      "其他非流動資產": 3495,
      "非流動資產合計": 4259187,
      "資產總額": 7225412,
      "流動負債": null,
      "短期借款": 161880,
      "應付帳款": 119477,
      "其他應付款": 75347,
      "其他流動負債": 2522,
      "流動負債合計": 359226,
      "非流動負債": null,
      "遞延所得稅負債": 60610,
      "其他非流動負債": 0,
      "非流動負債合計": 60610,
      "負債總額": 419836,
      "歸屬於母公司業主之權益": null,
      "股本": null,
      "普通股股本": 2689547,
      "股本合計": 2689547,
      "資本公積": null,
      "資本公積合計": 3022638,
      "保留盈餘": null,
      "法定盈餘公積": 708876,
      "特別盈餘公積": 460100,
      "未分配盈餘（或待彌補虧損）": 721285,
      "保留盈餘合計": 1890261,
      "其他權益": null,
      "國外營運機構財務報表換算之兌換差額": -796870,
      "其他權益合計": -796870,
      "歸屬於母公司業主之權益合計": 6805576,
      "權益總額": 6805576,
      "負債及權益總計": 7225412,
      "預收股款（權益項下）之約當發行股數（單位：股）": 0,
      "母公司暨子公司所持有之母公司庫藏股股數（單位：股）": 0
   }
}