{
   "field": [
      "Season",
      "流動資產",
      "現金及約當現金",
      "透過損益按公允價值衡量之金融資產－流動",
      "按攤銷後成本衡量之金融資產－流動",
      "應收帳款淨額",
      "其他應收款淨額",
      "本期所得稅資產",
      "存貨",
      "預付款項",
      "流動資產合計",
      "非流動資產",
      "按攤銷後成本衡量之金融資產－非流動",
      "不動產、廠房及設備",
      "使用權資產",
      "投資性不動產淨額",
      "無形資產",
      "遞延所得稅資產",
      "其他非流動資產",
      "非流動資產合計",
      "資產總額",
      "流動負債",
      "短期借款",
      "合約負債－流動",
      "應付票據",
      "應付帳款",
      "其他應付款",
      "本期所得稅負債",
      "租賃負債－流動",
      "流動負債合計",
      "非流動負債",
      "遞延所得稅負債",
      "租賃負債－非流動",
      "其他非流動負債",
      "非流動負債合計",
      "負債總額",
      "歸屬於母公司業主之權益",
      "股本",
      "普通股股本",
      "股本合計",
      "資本公積",
      "資本公積－發行溢價",
      "資本公積－受贈資產",
      "資本公積合計",
      "保留盈餘",
      "法定盈餘公積",
      "特別盈餘公積",
      "未分配盈餘（或待彌補虧損）",
      "保留盈餘合計",
      "其他權益",
      "國外營運機構財務報表換算之兌換差額",
      "其他權益合計",
      "歸屬於母公司業主之權益合計",
      "非控制權益",
      "權益總額",
      "負債及權益總計",
      "待註銷股本股數（單位：股）",
      "預收股款（權益項下）之約當發行股數（單位：股）",
      "母公司暨子公司所持有之母公司庫藏股股數（單位：股）"
   ],
   "data": {
      "Season": "2023/1",
      "流動資產": null,
      "現金及約當現金": 580791,
      "透過損益按公允價值衡量之金融資產－流動": 462970,
      "按攤銷後成本衡量之金融資產－流動": 679508,
      "應收帳款淨額": 112110,
      "其他應收款淨額": 42751,
      "本期所得稅資產": 12,
      "存貨": 597232,
      "預付款項": 30339,
      "流動資產合計": 2505713,
      "非流動資產": null,
      "按攤銷後成本衡量之金融資產－非流動": 60798,
      "不動產、廠房及設備": 364052,
      "使用權資產": 32394,
      "投資性不動產淨額": 167437,
      "無形資產": 100,
      "遞延所得稅資產": 21051,
      "其他非流動資產": 9417,
      "非流動資產合計": 655249,
      "資產總額": 3160962,
      "流動負債": null,
      "短期借款": 0,
      "合約負債－流動": 54464,
      "應付票據": 12920,
      "應付帳款": 203696,
      "其他應付款": 127128,
      "本期所得稅負債": 85386,
      "租賃負債－流動": 701,
      "流動負債合計": 484295,
      "非流動負債": null,
      "遞延所得稅負債": 280120,
      "租賃負債－非流動": 0,
      "其他非流動負債": 23373,
      "非流動負債合計": 303493,
      "負債總額": 787788,
      "歸屬於母公司業主之權益": null,
      "股本": null,
      "普通股股本": 799994,
      "股本合計": 799994,
      "資本公積": null,
      "資本公積－發行溢價": 33594,
      "資本公積－受贈資產": 291,
      "資本公積合計": 33885,
      "保留盈餘": null,
      "法定盈餘公積": 493893,
      "特別盈餘公積": 199263,
      "未分配盈餘（或待彌補虧損）": 904181,
      "保留盈餘合計": 1597337,
      "其他權益": null,
      "國外營運機構財務報表換算之兌換差額": -58042,
      "其他權益合計": -58042,
      "歸屬於母公司業主之權益合計": 2373174,
      "非控制權益": 0,
      "權益總額": 2373174,
      "負債及權益總計": 3160962,
      "待註銷股本股數（單位：股）": 0,
      "預收股款（權益項下）之約當發行股數（單位：股）": 0,
      "母公司暨子公司所持有之母公司庫藏股股數（單位：股）": 0
   }
}