{
   "field": [
      "Season",
      "流動資產",
      "現金及約當現金",
      "透過損益按公允價值衡量之金融資產－流動",
      "備供出售金融資產－流動淨額",
      "無活絡市場之債務工具投資－流動淨額",
      "應收票據淨額",
      "應收票據－關係人淨額",
      "應收帳款淨額",
      "應收帳款－關係人淨額",
      "應收建造合約款",
      "其他應收款淨額",
      "其他應收款－關係人淨額",
      "存貨",
      "預付款項",
      "其他流動資產",
      "流動資產合計",
      "非流動資產",
      "備供出售金融資產－非流動淨額",
      "採用權益法之投資淨額",
      "不動產、廠房及設備",
      "投資性不動產淨額",
      "無形資產",
      "遞延所得稅資產",
      "其他非流動資產",
      "非流動資產合計",
      "資產總計",
      "流動負債",
      "短期借款",
      "透過損益按公允價值衡量之金融負債－流動",
      "應付票據",
      "應付票據－關係人",
      "應付帳款",
      "應付帳款－關係人",
      "應付建造合約款",
      "其他應付款",
      "本期所得稅負債",
      "負債準備－流動",
      "其他流動負債",
      "流動負債合計",
      "非流動負債",
      "應付公司債",
      "長期借款",
      "負債準備－非流動",
      "遞延所得稅負債",
      "其他非流動負債",
      "非流動負債合計",
      "負債總計",
      "歸屬於母公司業主之權益",
      "股本",
      "普通股股本",
      "股本合計",
      "資本公積",
      "資本公積－發行溢價",
      "資本公積－庫藏股票交易",
      "資本公積－採用權益法認列關聯企業及合資股權淨值之變動數",
      "資本公積－合併溢額",
      "資本公積－員工認股權",
      "資本公積－認股權",
      "資本公積－其他",
      "資本公積合計",
      "保留盈餘",
      "法定盈餘公積",
      "特別盈餘公積",
      "未分配盈餘（或待彌補虧損）",
      "保留盈餘合計",
      "其他權益",
      "國外營運機構財務報表換算之兌換差額",
      "備供出售金融資產未實現損益",
      "其他權益合計",
      "庫藏股票",
      "歸屬於母公司業主之權益合計",
      "非控制權益",
      "權益總計",
      "負債及權益總計",
      "待註銷股本股數（單位：股）",
      "預收股款（權益項下）之約當發行股數（單位：股）",
      "母公司暨子公司所持有之母公司庫藏股股數（單位：股）"
   ],
   "data": {
      "Season": "2015/4",
      "流動資產": null,
      "現金及約當現金": 14919042,
      "透過損益按公允價值衡量之金融資產－流動": 265984,
      "備供出售金融資產－流動淨額": 1462871,
      "無活絡市場之債務工具投資－流動淨額": 141551,
      "應收票據淨額": 1006151,
      "應收票據－關係人淨額": 14943,
      "應收帳款淨額": 9329829,
      "應收帳款－關係人淨額": 194082,
      "應收建造合約款": 805488,
      "其他應收款淨額": 323881,
      "其他應收款－關係人淨額": 692340,
      "存貨": 11755227,
      "預付款項": 333968,
      "其他流動資產": 1047045,
      "流動資產合計": 42292402,
      "非流動資產": null,
      "備供出售金融資產－非流動淨額": 10905909,
      "採用權益法之投資淨額": 5464797,
      "不動產、廠房及設備": 15018217,
      "投資性不動產淨額": 2561444,
      "無形資產": 5541844,
      "遞延所得稅資產": 1183247,
      "其他非流動資產": 1466392,
      "非流動資產合計": 42141850,
      "資產總計": 84434252,
      "流動負債": null,
      "短期借款": 6619012,
      "透過損益按公允價值衡量之金融負債－流動": 15043,
      "應付票據": 112098,
      "應付票據－關係人": 1313,
      "應付帳款": 6628882,
      "應付帳款－關係人": 95766,
      "應付建造合約款": 367467,
      "其他應付款": 4863815,
      "本期所得稅負債": 555477,
      "負債準備－流動": 256979,
      "其他流動負債": 3199186,
      "流動負債合計": 22715038,
      "非流動負債": null,
      "應付公司債": 3000000,
      "長期借款": 2300299,
      "負債準備－非流動": 230265,
      "遞延所得稅負債": 2317721,
      "其他非流動負債": 2438425,
      "非流動負債合計": 10286710,
      "負債總計": 33001748,
      "歸屬於母公司業主之權益": null,
      "股本": null,
      "普通股股本": 20026929,
      "股本合計": 20026929,
      "資本公積": null,
      "資本公積－發行溢價": 7028330,
      "資本公積－庫藏股票交易": 227397,
      "資本公積－採用權益法認列關聯企業及合資股權淨值之變動數": 225083,
      "資本公積－合併溢額": 139800,
      "資本公積－員工認股權": 212,
      "資本公積－認股權": 0,
      "資本公積－其他": 17595,
      "資本公積合計": 7638417,
      "保留盈餘": null,
      "法定盈餘公積": 5412342,
      "特別盈餘公積": 3640779,
      "未分配盈餘（或待彌補虧損）": 10310158,
      "保留盈餘合計": 19363279,
      "其他權益": null,
      "國外營運機構財務報表換算之兌換差額": 13030,
      "備供出售金融資產未實現損益": 743950,
      "其他權益合計": 756980,
      "庫藏股票": -321563,
      "歸屬於母公司業主之權益合計": 47464042,
      "非控制權益": 3968462,
      "權益總計": 51432504,
      "負債及權益總計": 84434252,
      "待註銷股本股數（單位：股）": 0,
      "預收股款（權益項下）之約當發行股數（單位：股）": 0,
      "母公司暨子公司所持有之母公司庫藏股股數（單位：股）": 22443022
   }
}