{
   "field": [
      "Season",
      "流動資產",
      "現金及約當現金",
      "備供出售金融資產－流動淨額",
      "應收票據淨額",
      "應收帳款淨額",
      "其他應收款淨額",
      "本期所得稅資產",
      "存貨",
      "預付款項",
      "其他流動資產",
      "流動資產合計",
      "非流動資產",
      "不動產、廠房及設備",
      "投資性不動產淨額",
      "無形資產",
      "遞延所得稅資產",
      "其他非流動資產",
      "非流動資產合計",
      "資產總計",
      "流動負債",
      "短期借款",
      "應付票據",
      "應付帳款",
      "其他應付款",
      "本期所得稅負債",
      "其他流動負債",
      "流動負債合計",
      "非流動負債",
      "長期借款",
      "其他非流動負債",
      "非流動負債合計",
      "負債總計",
      "歸屬於母公司業主之權益",
      "股本",
      "普通股股本",
      "股本合計",
      "資本公積",
      "資本公積合計",
      "保留盈餘",
      "法定盈餘公積",
      "特別盈餘公積",
      "未分配盈餘（或待彌補虧損）",
      "保留盈餘合計",
      "其他權益",
      "其他權益合計",
      "歸屬於母公司業主之權益合計",
      "非控制權益",
      "權益總計",
      "負債及權益總計",
      "待註銷股本股數（單位：股）",
      "預收股款（權益項下）之約當發行股數（單位：股）",
      "母公司暨子公司所持有之母公司庫藏股股數（單位：股）"
   ],
   "data": {
      "Season": "2015/4",
      "流動資產": null,
      "現金及約當現金": 167901,
      "備供出售金融資產－流動淨額": 0,
      "應收票據淨額": 1567,
      "應收帳款淨額": 61483,
      "其他應收款淨額": 14649,
      "本期所得稅資產": 0,
      "存貨": 78823,
      "預付款項": 21864,
      "其他流動資產": 1896,
      "流動資產合計": 348183,
      "非流動資產": null,
      "不動產、廠房及設備": 1116742,
      "投資性不動產淨額": 47848,
      "無形資產": 2145,
      "遞延所得稅資產": 5851,
      "其他非流動資產": 79214,
      "非流動資產合計": 1251800,
      "資產總計": 1599983,
      "流動負債": null,
      "短期借款": 196909,
      "應付票據": 4590,
      "應付帳款": 94847,
      "其他應付款": 147872,
      "本期所得稅負債": 12459,
      "其他流動負債": 116861,
      "流動負債合計": 573538,
      "非流動負債": null,
      "長期借款": 190000,
      "其他非流動負債": 27213,
      "非流動負債合計": 217213,
      "負債總計": 790751,
      "歸屬於母公司業主之權益": null,
      "股本": null,
      "普通股股本": 674910,
      "股本合計": 674910,
      "資本公積": null,
      "資本公積合計": 127463,
      "保留盈餘": null,
      "法定盈餘公積": 97776,
      "特別盈餘公積": 0,
      "未分配盈餘（或待彌補虧損）": -120650,
      "保留盈餘合計": -22874,
      "其他權益": null,
      "其他權益合計": 19335,
      "歸屬於母公司業主之權益合計": 798834,
      "非控制權益": 10398,
      "權益總計": 809232,
      "負債及權益總計": 1599983,
      "待註銷股本股數（單位：股）": 0,
      "預收股款（權益項下）之約當發行股數（單位：股）": 0,
      "母公司暨子公司所持有之母公司庫藏股股數（單位：股）": 0
   }
}