{
   "field": [
      "Season",
      "流動資產",
      "現金及約當現金",
      "透過損益按公允價值衡量之金融資產－流動",
      "按攤銷後成本衡量之金融資產－流動",
      "應收票據淨額",
      "應收帳款淨額",
      "其他應收款淨額",
      "存貨",
      "其他流動資產",
      "流動資產合計",
      "非流動資產",
      "按攤銷後成本衡量之金融資產－非流動",
      "不動產、廠房及設備",
      "使用權資產",
      "投資性不動產淨額",
      "無形資產",
      "遞延所得稅資產",
      "其他非流動資產",
      "非流動資產合計",
      "資產總額",
      "流動負債",
      "合約負債－流動",
      "應付票據",
      "應付帳款",
      "其他應付款",
      "租賃負債－流動",
      "其他流動負債",
      "流動負債合計",
      "非流動負債",
      "租賃負債－非流動",
      "其他非流動負債",
      "非流動負債合計",
      "負債總額",
      "股本",
      "普通股股本",
      "股本合計",
      "資本公積",
      "資本公積－發行溢價",
      "資本公積－合併溢額",
      "資本公積合計",
      "保留盈餘",
      "法定盈餘公積",
      "未分配盈餘（或待彌補虧損）",
      "保留盈餘合計",
      "其他權益",
      "其他權益合計",
      "庫藏股票",
      "權益總額",
      "負債及權益總計",
      "預收股款（權益項下）之約當發行股數（單位：股）",
      "母公司暨子公司所持有之母公司庫藏股股數（單位：股）"
   ],
   "data": {
      "Season": "2020/3",
      "流動資產": null,
      "現金及約當現金": 525543,
      "透過損益按公允價值衡量之金融資產－流動": 100302,
      "按攤銷後成本衡量之金融資產－流動": 1306014,
      "應收票據淨額": 748,
      "應收帳款淨額": 90996,
      "其他應收款淨額": 1524,
      "存貨": 2768023,
      "其他流動資產": 21790,
      "流動資產合計": 4814940,
      "非流動資產": null,
      "按攤銷後成本衡量之金融資產－非流動": 62200,
      "不動產、廠房及設備": 414016,
      "使用權資產": 2516586,
      "投資性不動產淨額": 194663,
      "無形資產": 44796,
      "遞延所得稅資產": 42916,
      "其他非流動資產": 161889,
      "非流動資產合計": 3437066,
      "資產總額": 8252006,
      "流動負債": null,
      "合約負債－流動": 563258,
      "應付票據": 1301,
      "應付帳款": 1666649,
      "其他應付款": 679413,
      "租賃負債－流動": 599320,
      "其他流動負債": 29070,
      "流動負債合計": 3539011,
      "非流動負債": null,
      "租賃負債－非流動": 1957661,
      "其他非流動負債": 215701,
      "非流動負債合計": 2173362,
      "負債總額": 5712373,
      "股本": null,
      "普通股股本": 991729,
      "股本合計": 991729,
      "資本公積": null,
      "資本公積－發行溢價": 435568,
      "資本公積－合併溢額": 726,
      "資本公積合計": 436294,
      "保留盈餘": null,
      "法定盈餘公積": 611158,
      "未分配盈餘（或待彌補虧損）": 500452,
      "保留盈餘合計": 1111610,
      "其他權益": null,
      "其他權益合計": 0,
      "庫藏股票": 0,
      "權益總額": 2539633,
      "負債及權益總計": 8252006,
      "預收股款（權益項下）之約當發行股數（單位：股）": 0,
      "母公司暨子公司所持有之母公司庫藏股股數（單位：股）": 0
   }
}