{
   "field": [
      "Season",
      "流動資產",
      "現金及約當現金",
      "透過損益按公允價值衡量之金融資產－流動",
      "應收帳款淨額",
      "存貨",
      "其他流動資產",
      "流動資產合計",
      "非流動資產",
      "透過損益按公允價值衡量之金融資產－非流動",
      "按攤銷後成本衡量之金融資產－非流動",
      "不動產、廠房及設備",
      "使用權資產",
      "遞延所得稅資產",
      "其他非流動資產",
      "非流動資產合計",
      "資產總額",
      "流動負債",
      "短期借款",
      "應付短期票券",
      "應付帳款",
      "租賃負債－流動",
      "其他流動負債",
      "流動負債合計",
      "非流動負債",
      "長期借款",
      "遞延所得稅負債",
      "租賃負債－非流動",
      "非流動負債合計",
      "負債總額",
      "歸屬於母公司業主之權益",
      "股本",
      "普通股股本",
      "預收股本",
      "股本合計",
      "資本公積",
      "資本公積合計",
      "保留盈餘",
      "法定盈餘公積",
      "特別盈餘公積",
      "未分配盈餘（或待彌補虧損）",
      "保留盈餘合計",
      "其他權益",
      "國外營運機構財務報表換算之兌換差額",
      "其他權益合計",
      "歸屬於母公司業主之權益合計",
      "權益總額",
      "負債及權益總計",
      "待註銷股本股數（單位：股）",
      "預收股款（權益項下）之約當發行股數（單位：股）",
      "母公司暨子公司所持有之母公司庫藏股股數（單位：股）"
   ],
   "data": {
      "Season": "2021/4",
      "流動資產": null,
      "現金及約當現金": 3999433,
      "透過損益按公允價值衡量之金融資產－流動": 104006,
      "應收帳款淨額": 1352595,
      "存貨": 519871,
      "其他流動資產": 95349,
      "流動資產合計": 6071254,
      "非流動資產": null,
      "透過損益按公允價值衡量之金融資產－非流動": 197419,
      "按攤銷後成本衡量之金融資產－非流動": 1264067,
      "不動產、廠房及設備": 1386444,
      "使用權資產": 37608,
      "遞延所得稅資產": 22267,
      "其他非流動資產": 118033,
      "非流動資產合計": 3025838,
      "資產總額": 9097092,
      "流動負債": null,
      "短期借款": 1737760,
      "應付短期票券": 99971,
      "應付帳款": 588508,
      "租賃負債－流動": 31228,
      "其他流動負債": 399998,
      "流動負債合計": 2857465,
      "非流動負債": null,
      "長期借款": 1150000,
      "遞延所得稅負債": 667215,
      "租賃負債－非流動": 6713,
      "非流動負債合計": 1823928,
      "負債總額": 4681393,
      "歸屬於母公司業主之權益": null,
      "股本": null,
      "普通股股本": 626712,
      "預收股本": 0,
      "股本合計": 626712,
      "資本公積": null,
      "資本公積合計": 981485,
      "保留盈餘": null,
      "法定盈餘公積": 610265,
      "特別盈餘公積": 310459,
      "未分配盈餘（或待彌補虧損）": 2231720,
      "保留盈餘合計": 3152444,
      "其他權益": null,
      "國外營運機構財務報表換算之兌換差額": -344942,
      "其他權益合計": -344942,
      "歸屬於母公司業主之權益合計": 4415699,
      "權益總額": 4415699,
      "負債及權益總計": 9097092,
      "待註銷股本股數（單位：股）": 0,
      "預收股款（權益項下）之約當發行股數（單位：股）": 0,
      "母公司暨子公司所持有之母公司庫藏股股數（單位：股）": 0
   }
}