{
   "field": [
      "Season",
      "流動資產",
      "現金及約當現金",
      "避險之金融資產－流動",
      "應收帳款淨額",
      "本期所得稅資產",
      "存貨",
      "其他流動資產",
      "流動資產合計",
      "非流動資產",
      "不動產、廠房及設備",
      "使用權資產",
      "無形資產",
      "遞延所得稅資產",
      "其他非流動資產",
      "非流動資產合計",
      "資產總額",
      "流動負債",
      "短期借款",
      "應付短期票券",
      "避險之金融負債－流動",
      "應付帳款",
      "其他應付款",
      "本期所得稅負債",
      "負債準備－流動",
      "其他流動負債",
      "流動負債合計",
      "非流動負債",
      "應付公司債",
      "長期借款",
      "負債準備－非流動",
      "租賃負債－非流動",
      "其他非流動負債",
      "非流動負債合計",
      "負債總額",
      "股本",
      "普通股股本",
      "股本合計",
      "資本公積",
      "資本公積合計",
      "保留盈餘",
      "法定盈餘公積",
      "未分配盈餘（或待彌補虧損）",
      "保留盈餘合計",
      "權益總額",
      "負債及權益總計",
      "預收股款（權益項下）之約當發行股數（單位：股）",
      "母公司暨子公司所持有之母公司庫藏股股數（單位：股）"
   ],
   "data": {
      "Season": "2022/3",
      "流動資產": null,
      "現金及約當現金": 16672796,
      "避險之金融資產－流動": 365,
      "應收帳款淨額": 276379,
      "本期所得稅資產": 216549,
      "存貨": 2540862,
      "其他流動資產": 7169166,
      "流動資產合計": 26876117,
      "非流動資產": null,
      "不動產、廠房及設備": 136028,
      "使用權資產": 448422,
      "無形資產": 361133157,
      "遞延所得稅資產": 6603871,
      "其他非流動資產": 2097943,
      "非流動資產合計": 370419421,
      "資產總額": 397295538,
      "流動負債": null,
      "短期借款": 13578,
      "應付短期票券": 21963554,
      "避險之金融負債－流動": 0,
      "應付帳款": 505537,
      "其他應付款": 3649447,
      "本期所得稅負債": 0,
      "負債準備－流動": 1169562,
      "其他流動負債": 1036294,
      "流動負債合計": 28337972,
      "非流動負債": null,
      "應付公司債": 27472466,
      "長期借款": 217620812,
      "負債準備－非流動": 2162721,
      "租賃負債－非流動": 271418,
      "其他非流動負債": 55774741,
      "非流動負債合計": 303302158,
      "負債總額": 331640130,
      "股本": null,
      "普通股股本": 56282930,
      "股本合計": 56282930,
      "資本公積": null,
      "資本公積合計": 172981,
      "保留盈餘": null,
      "法定盈餘公積": 4212542,
      "未分配盈餘（或待彌補虧損）": 4986955,
      "保留盈餘合計": 9199497,
      "權益總額": 65655408,
      "負債及權益總計": 397295538,
      "預收股款（權益項下）之約當發行股數（單位：股）": 0,
      "母公司暨子公司所持有之母公司庫藏股股數（單位：股）": 0
   }
}