{
   "field": [
      "Season",
      "流動資產",
      "現金及約當現金",
      "透過損益按公允價值衡量之金融資產－流動",
      "應收票據淨額",
      "應收帳款淨額",
      "其他應收款淨額",
      "存貨",
      "預付款項",
      "其他流動資產",
      "流動資產合計",
      "非流動資產",
      "以成本衡量之金融資產－非流動淨額",
      "採用權益法之投資淨額",
      "不動產、廠房及設備",
      "無形資產",
      "其他非流動資產",
      "非流動資產合計",
      "資產總額",
      "流動負債",
      "短期借款",
      "透過損益按公允價值衡量之金融負債－流動",
      "應付票據",
      "應付帳款",
      "其他應付款",
      "當期所得稅負債",
      "其他流動負債",
      "流動負債合計",
      "非流動負債",
      "應付公司債",
      "其他非流動負債",
      "非流動負債合計",
      "負債總額",
      "歸屬於母公司業主之權益",
      "股本",
      "普通股股本",
      "股本合計",
      "資本公積",
      "資本公積－發行溢價",
      "資本公積合計",
      "保留盈餘",
      "法定盈餘公積",
      "未分配盈餘（或待彌補虧損）",
      "保留盈餘合計",
      "其他權益",
      "其他權益－其他",
      "其他權益合計",
      "庫藏股票",
      "歸屬於母公司業主之權益合計",
      "非控制權益",
      "權益總額",
      "預收股款（權益項下）之約當發行股數（單位：股）",
      "母公司暨子公司所持有之母公司庫藏股股數（單位：股）"
   ],
   "data": {
      "Season": "2013/4",
      "流動資產": null,
      "現金及約當現金": 2319848,
      "透過損益按公允價值衡量之金融資產－流動": 1213547,
      "應收票據淨額": 4762,
      "應收帳款淨額": 58550,
      "其他應收款淨額": 7529,
      "存貨": 20230,
      "預付款項": 7318,
      "其他流動資產": 300,
      "流動資產合計": 3632084,
      "非流動資產": null,
      "以成本衡量之金融資產－非流動淨額": 25894,
      "採用權益法之投資淨額": 667540,
      "不動產、廠房及設備": 819637,
      "無形資產": 87697,
      "其他非流動資產": 13051,
      "非流動資產合計": 1613819,
      "資產總額": 5245903,
      "流動負債": null,
      "短期借款": 510000,
      "透過損益按公允價值衡量之金融負債－流動": 58695,
      "應付票據": 37329,
      "應付帳款": 31678,
      "其他應付款": 51469,
      "當期所得稅負債": 25717,
      "其他流動負債": 109539,
      "流動負債合計": 824427,
      "非流動負債": null,
      "應付公司債": 1140150,
      "其他非流動負債": 52730,
      "非流動負債合計": 1192880,
      "負債總額": 2017307,
      "歸屬於母公司業主之權益": null,
      "股本": null,
      "普通股股本": 847726,
      "股本合計": 847726,
      "資本公積": null,
      "資本公積－發行溢價": 243390,
      "資本公積合計": 243390,
      "保留盈餘": null,
      "法定盈餘公積": 266246,
      "未分配盈餘（或待彌補虧損）": 348123,
      "保留盈餘合計": 614369,
      "其他權益": null,
      "其他權益－其他": 72435,
      "其他權益合計": 72435,
      "庫藏股票": 0,
      "歸屬於母公司業主之權益合計": 1777920,
      "非控制權益": 1450676,
      "權益總額": 3228596,
      "預收股款（權益項下）之約當發行股數（單位：股）": 0,
      "母公司暨子公司所持有之母公司庫藏股股數（單位：股）": 0
   }
}