{
   "field": [
      "Season",
      "流動資產",
      "現金及約當現金",
      "透過損益按公允價值衡量之金融資產－流動",
      "透過其他綜合損益按公允價值衡量之金融資產－流動",
      "按攤銷後成本衡量之金融資產－流動",
      "應收票據淨額",
      "應收帳款淨額",
      "應收帳款－關係人淨額",
      "其他應收款淨額",
      "本期所得稅資產",
      "存貨",
      "預付款項",
      "流動資產合計",
      "非流動資產",
      "透過其他綜合損益按公允價值衡量之金融資產－非流動",
      "採用權益法之投資",
      "不動產、廠房及設備",
      "使用權資產",
      "投資性不動產淨額",
      "無形資產",
      "遞延所得稅資產",
      "其他非流動資產",
      "非流動資產合計",
      "資產總額",
      "流動負債",
      "應付票據",
      "應付帳款",
      "應付帳款－關係人",
      "其他應付款",
      "本期所得稅負債",
      "負債準備－流動",
      "租賃負債－流動",
      "其他流動負債",
      "流動負債合計",
      "非流動負債",
      "應付公司債",
      "遞延所得稅負債",
      "租賃負債－非流動",
      "其他非流動負債",
      "非流動負債合計",
      "負債總額",
      "歸屬於母公司業主之權益",
      "股本",
      "普通股股本",
      "股本合計",
      "資本公積",
      "資本公積－發行溢價",
      "資本公積－庫藏股票交易",
      "資本公積－實際取得或處分子公司股權價格與帳面價值差額",
      "資本公積-認列對子公司所有權權益變動數",
      "資本公積－採用權益法認列關聯企業及合資股權淨值之變動數",
      "資本公積－認股權",
      "資本公積合計",
      "保留盈餘",
      "法定盈餘公積",
      "未分配盈餘（或待彌補虧損）",
      "保留盈餘合計",
      "其他權益",
      "國外營運機構財務報表換算之兌換差額",
      "透過其他綜合損益按公允價值衡量之金融資產未實現評價損益",
      "其他權益合計",
      "庫藏股票",
      "歸屬於母公司業主之權益合計",
      "非控制權益",
      "權益總額",
      "負債及權益總計",
      "預收股款（權益項下）之約當發行股數（單位：股）",
      "母公司暨子公司所持有之母公司庫藏股股數（單位：股）"
   ],
   "data": {
      "Season": "2021/3",
      "流動資產": null,
      "現金及約當現金": 877039,
      "透過損益按公允價值衡量之金融資產－流動": 16481,
      "透過其他綜合損益按公允價值衡量之金融資產－流動": 117591,
      "按攤銷後成本衡量之金融資產－流動": 142914,
      "應收票據淨額": 1465,
      "應收帳款淨額": 511386,
      "應收帳款－關係人淨額": 1894,
      "其他應收款淨額": 111,
      "本期所得稅資產": 3175,
      "存貨": 186376,
      "預付款項": 35339,
      "流動資產合計": 1893771,
      "非流動資產": null,
      "透過其他綜合損益按公允價值衡量之金融資產－非流動": 328454,
      "採用權益法之投資": 37475,
      "不動產、廠房及設備": 432799,
      "使用權資產": 27382,
      "投資性不動產淨額": 47967,
      "無形資產": 3012,
      "遞延所得稅資產": 21182,
      "其他非流動資產": 8029,
      "非流動資產合計": 906300,
      "資產總額": 2800071,
      "流動負債": null,
      "應付票據": 2061,
      "應付帳款": 265312,
      "應付帳款－關係人": 34282,
      "其他應付款": 112105,
      "本期所得稅負債": 30916,
      "負債準備－流動": 13429,
      "租賃負債－流動": 13699,
      "其他流動負債": 27526,
      "流動負債合計": 499330,
      "非流動負債": null,
      "應付公司債": 337405,
      "遞延所得稅負債": 45277,
      "租賃負債－非流動": 14310,
      "其他非流動負債": 21462,
      "非流動負債合計": 418454,
      "負債總額": 917784,
      "歸屬於母公司業主之權益": null,
      "股本": null,
      "普通股股本": 720402,
      "股本合計": 720402,
      "資本公積": null,
      "資本公積－發行溢價": 196344,
      "資本公積－庫藏股票交易": 8509,
      "資本公積－實際取得或處分子公司股權價格與帳面價值差額": 1625,
      "資本公積-認列對子公司所有權權益變動數": 201,
      "資本公積－採用權益法認列關聯企業及合資股權淨值之變動數": 0,
      "資本公積－認股權": 9358,
      "資本公積合計": 216037,
      "保留盈餘": null,
      "法定盈餘公積": 333203,
      "未分配盈餘（或待彌補虧損）": 562609,
      "保留盈餘合計": 895812,
      "其他權益": null,
      "國外營運機構財務報表換算之兌換差額": -19589,
      "透過其他綜合損益按公允價值衡量之金融資產未實現評價損益": 45458,
      "其他權益合計": 25869,
      "庫藏股票": 0,
      "歸屬於母公司業主之權益合計": 1858120,
      "非控制權益": 24167,
      "權益總額": 1882287,
      "負債及權益總計": 2800071,
      "預收股款（權益項下）之約當發行股數（單位：股）": 0,
      "母公司暨子公司所持有之母公司庫藏股股數（單位：股）": 0
   }
}